<nfe>
    <notaFiscal>
        <dadosPrestador>
            <dataEmissao></dataEmissao>
            <im></im>
            <numeroRps></numeroRps>
        </dadosPrestador>
        <dadosServico>
            <bairro></bairro>
            <cep></cep>
            <cidade></cidade>
            <complemento></complemento>
            <logradouro></logradouro>
            <numero></numero>
            <pais></pais>
            <uf></uf>
        </dadosServico>
        <dadosTomador>
            <bairro></bairro>
            <cep></cep>
            <cidade></cidade>
            <complemento></complemento>
            <documento></documento>
            <email></email>
            <ie></ie>
            <logradouro></logradouro>
            <nomeTomador></nomeTomador>
            <numero></numero>
            <pais></pais>
            <tipoDoc></tipoDoc>
            <uf></uf>
        </dadosTomador>
        <detalheServico>
            <cofins></cofins>
            <csll></csll>
            <deducaoMaterial></deducaoMaterial>
            <descontoIncondicional></descontoIncondicional>
            <inss></inss>
            <ir></ir>
            <issRetido></issRetido>
            <item>
                <aliquota></aliquota>
                <codigo></codigo>
                <descricao></descricao>
                <valor></valor>
            </item>
            <obs></obs>
            <pisPasep></pisPasep>
        </detalheServico>
    </notaFiscal>
</nfe>
